{"1":{"condition":"","section":1,"trigger":"start"},"100":{"condition":"26","section":100,"trigger":"level"},"101":{"condition":"28","section":101,"trigger":"level"},"102":{"condition":"29","section":102,"trigger":"level"},"103":{"condition":"24","section":103,"trigger":"level"},"104":{"condition":"30","section":104,"trigger":"level"},"106":{"condition":"23","section":106,"trigger":"level"},"107":{"condition":"146","section":107,"trigger":"first"},"151":{"condition":"11","section":151,"trigger":"level"},"2":{"condition":"8","section":2,"trigger":"level"},"3":{"condition":"9","section":3,"trigger":"level"},"30":{"condition":"157","section":30,"trigger":"first"},"34":{"condition":"23","section":34,"trigger":"first"},"35":{"condition":"25","section":35,"trigger":"first"},"36":{"condition":"131","section":36,"trigger":"first"},"37":{"condition":"17","section":37,"trigger":"level"},"39":{"condition":"28","section":39,"trigger":"first"},"4":{"condition":"10","section":4,"trigger":"level"},"40":{"condition":"168","section":40,"trigger":"first"},"41":{"condition":"20","section":41,"trigger":"first"},"42":{"condition":"31","section":42,"trigger":"first"},"43":{"condition":"213","section":43,"trigger":"first"},"45":{"condition":"140","section":45,"trigger":"first"},"46":{"condition":"53","section":46,"trigger":"first"},"47":{"condition":"51","section":47,"trigger":"first"},"48":{"condition":"137","section":48,"trigger":"first"},"49":{"condition":"27","section":49,"trigger":"first"},"5":{"condition":"13","section":5,"trigger":"level"},"50":{"condition":"211","section":50,"trigger":"first"},"51":{"condition":"209","section":51,"trigger":"first"},"52":{"condition":"203","section":52,"trigger":"first"},"55":{"condition":"20","section":55,"trigger":"level"},"56":{"condition":"23","section":56,"trigger":"level"},"58":{"condition":"138","section":58,"trigger":"first"},"59":{"condition":"175","section":59,"trigger":"first"},"6":{"condition":"12","section":6,"trigger":"level"},"62":{"condition":"75","section":62,"trigger":"first"},"63":{"condition":"192","section":63,"trigger":"first"},"64":{"condition":"49","section":64,"trigger":"first"},"65":{"condition":"21","section":65,"trigger":"first"},"66":{"condition":"311","section":66,"trigger":"first"},"67":{"condition":"191","section":67,"trigger":"first"},"68":{"condition":"9","section":68,"trigger":"first"},"69":{"condition":"174","section":69,"trigger":"first"},"70":{"condition":"179","section":70,"trigger":"first"},"72":{"condition":"199","section":72,"trigger":"first"},"73":{"condition":"262","section":73,"trigger":"first"},"74":{"condition":"142","section":74,"trigger":"first"},"75":{"condition":"124","section":75,"trigger":"first"},"76":{"condition":"144","section":76,"trigger":"first"},"88":{"condition":"20","section":88,"trigger":"level"},"89":{"condition":"18","section":89,"trigger":"level"},"90":{"condition":"16","section":90,"trigger":"level"},"91":{"condition":"19","section":91,"trigger":"level"},"92":{"condition":"14","section":92,"trigger":"level"},"93":{"condition":"25","section":93,"trigger":"first"},"94":{"condition":"15","section":94,"trigger":"level"},"95":{"condition":"20","section":95,"trigger":"level"},"96":{"condition":"21","section":96,"trigger":"level"},"97":{"condition":"27","section":97,"trigger":"level"},"98":{"condition":"22","section":98,"trigger":"level"},"99":{"condition":"25","section":99,"trigger":"level"}}