{"1":{"attr1":"atk,330;","attr3":"atk,330;hit,18;parry,12;","attr4":"def,330;arp,12;critical,12;","attr5":"hp,2900;dodge,18;resilience,12;","hall_stone_limit":100,"hall_stone_output":10,"hall_wood_limit":100,"hall_wood_output":10,"level":1,"monster_reward":"20377,10,15;20378,10,15;","output":"20377,10;20378,10;","store_limit":"20377,100;20378,100;","update_cost1":"20377,0;20378,0;","update_cost2":"20377,0;20378,0;","update_cost3":"20377,60;20378,20;","update_cost4":"20377,60;20378,20;","update_cost5":"20377,20;20378,60;","update_limit":42},"10":{"attr1":"atk,1970;","attr3":"atk,1970;hit,110;parry,73;","attr4":"def,1970;arp,73;critical,73;","attr5":"hp,17700;dodge,110;resilience,73;","hall_stone_limit":190,"hall_stone_output":19,"hall_wood_limit":190,"hall_wood_output":19,"level":10,"monster_reward":"20377,19,29;20378,19,29;","output":"20377,19;20378,19;","store_limit":"20377,190;20378,190;","update_cost1":"20377,1630;20378,2710;","update_cost2":"","update_cost3":"20377,1630;20378,540;","update_cost4":"20377,1630;20378,540;","update_cost5":"20377,540;20378,1630;","update_limit":56},"11":{"attr1":"atk,2190;","attr3":"atk,2190;hit,122;parry,81;","attr4":"def,2190;arp,81;critical,81;","attr5":"hp,19700;dodge,122;resilience,81;","hall_stone_limit":200,"hall_stone_output":20,"hall_wood_limit":200,"hall_wood_output":20,"level":11,"monster_reward":"20377,20,30;20378,20,30;","output":"20377,20;20378,20;","store_limit":"20377,200;20378,200;","update_cost1":"20377,1890;20378,3140;","update_cost2":"","update_cost3":"20377,1890;20378,630;","update_cost4":"20377,1890;20378,630;","update_cost5":"20377,630;20378,1890;","update_limit":58},"12":{"attr1":"atk,2420;","attr3":"atk,2420;hit,134;parry,90;","attr4":"def,2420;arp,90;critical,90;","attr5":"hp,21800;dodge,134;resilience,90;","hall_stone_limit":210,"hall_stone_output":21,"hall_wood_limit":210,"hall_wood_output":21,"level":12,"monster_reward":"20377,21,32;20378,21,32;","output":"20377,21;20378,21;","store_limit":"20377,210;20378,210;","update_cost1":"20377,2170;20378,3620;","update_cost2":"","update_cost3":"20377,2170;20378,720;","update_cost4":"20377,2170;20378,720;","update_cost5":"20377,720;20378,2170;","update_limit":60},"13":{"attr1":"atk,2650;","attr3":"atk,2650;hit,147;parry,98;","attr4":"def,2650;arp,98;critical,98;","attr5":"hp,23800;dodge,147;resilience,98;","hall_stone_limit":220,"hall_stone_output":22,"hall_wood_limit":220,"hall_wood_output":22,"level":13,"monster_reward":"20377,22,33;20378,22,33;","output":"20377,22;20378,22;","store_limit":"20377,220;20378,220;","update_cost1":"20377,2490;20378,4150;","update_cost2":"","update_cost3":"20377,2490;20378,830;","update_cost4":"20377,2490;20378,830;","update_cost5":"20377,830;20378,2490;","update_limit":62},"14":{"attr1":"atk,2890;","attr3":"atk,2890;hit,161;parry,107;","attr4":"def,2890;arp,107;critical,107;","attr5":"hp,26000;dodge,161;resilience,107;","hall_stone_limit":230,"hall_stone_output":23,"hall_wood_limit":230,"hall_wood_output":23,"level":14,"monster_reward":"20377,23,35;20378,23,35;","output":"20377,23;20378,23;","store_limit":"20377,230;20378,230;","update_cost1":"20377,2840;20378,4730;","update_cost2":"","update_cost3":"20377,2840;20378,950;","update_cost4":"20377,2840;20378,950;","update_cost5":"20377,950;20378,2840;","update_limit":64},"15":{"attr1":"atk,3140;","attr3":"atk,3140;hit,174;parry,116;","attr4":"def,3140;arp,116;critical,116;","attr5":"hp,28200;dodge,174;resilience,116;","hall_stone_limit":240,"hall_stone_output":24,"hall_wood_limit":240,"hall_wood_output":24,"level":15,"monster_reward":"20377,24,36;20378,24,36;","output":"20377,24;20378,24;","store_limit":"20377,240;20378,240;","update_cost1":"20377,3230;20378,5380;","update_cost2":"","update_cost3":"20377,3230;20378,1080;","update_cost4":"20377,3230;20378,1080;","update_cost5":"20377,1080;20378,3230;","update_limit":66},"16":{"attr1":"atk,3390;","attr3":"atk,3390;hit,189;parry,126;","attr4":"def,3390;arp,126;critical,126;","attr5":"hp,30500;dodge,189;resilience,126;","hall_stone_limit":250,"hall_stone_output":25,"hall_wood_limit":250,"hall_wood_output":25,"level":16,"monster_reward":"20377,25,38;20378,25,38;","output":"20377,25;20378,25;","store_limit":"20377,250;20378,250;","update_cost1":"20377,3630;20378,6050;","update_cost2":"","update_cost3":"20377,3630;20378,1210;","update_cost4":"20377,3630;20378,1210;","update_cost5":"20377,1210;20378,3630;","update_limit":68},"17":{"attr1":"atk,3650;","attr3":"atk,3650;hit,203;parry,135;","attr4":"def,3650;arp,135;critical,135;","attr5":"hp,32900;dodge,203;resilience,135;","hall_stone_limit":260,"hall_stone_output":26,"hall_wood_limit":260,"hall_wood_output":26,"level":17,"monster_reward":"20377,26,39;20378,26,39;","output":"20377,26;20378,26;","store_limit":"20377,260;20378,260;","update_cost1":"20377,4080;20378,6790;","update_cost2":"","update_cost3":"20377,4080;20378,1360;","update_cost4":"20377,4080;20378,1360;","update_cost5":"20377,1360;20378,4080;","update_limit":70},"18":{"attr1":"atk,3920;","attr3":"atk,3920;hit,218;parry,145;","attr4":"def,3920;arp,145;critical,145;","attr5":"hp,35300;dodge,218;resilience,145;","hall_stone_limit":270,"hall_stone_output":27,"hall_wood_limit":270,"hall_wood_output":27,"level":18,"monster_reward":"20377,27,41;20378,27,41;","output":"20377,27;20378,27;","store_limit":"20377,270;20378,270;","update_cost1":"20377,4550;20378,7580;","update_cost2":"","update_cost3":"20377,4550;20378,1520;","update_cost4":"20377,4550;20378,1520;","update_cost5":"20377,1520;20378,4550;","update_limit":72},"19":{"attr1":"atk,4200;","attr3":"atk,4200;hit,233;parry,156;","attr4":"def,4200;arp,156;critical,156;","attr5":"hp,37800;dodge,233;resilience,156;","hall_stone_limit":280,"hall_stone_output":28,"hall_wood_limit":280,"hall_wood_output":28,"level":19,"monster_reward":"20377,28,42;20378,28,42;","output":"20377,28;20378,28;","store_limit":"20377,280;20378,280;","update_cost1":"20377,5050;20378,8420;","update_cost2":"","update_cost3":"20377,5050;20378,1680;","update_cost4":"20377,5050;20378,1680;","update_cost5":"20377,1680;20378,5050;","update_limit":74},"2":{"attr1":"atk,480;","attr3":"atk,480;hit,27;parry,18;","attr4":"def,480;arp,18;critical,18;","attr5":"hp,4300;dodge,27;resilience,18;","hall_stone_limit":110,"hall_stone_output":11,"hall_wood_limit":110,"hall_wood_output":11,"level":2,"monster_reward":"20377,11,17;20378,11,17;","output":"20377,11;20378,11;","store_limit":"20377,110;20378,110;","update_cost1":"20377,140;20378,240;","update_cost2":"","update_cost3":"20377,140;20378,50;","update_cost4":"20377,140;20378,50;","update_cost5":"20377,50;20378,140;","update_limit":42},"20":{"attr1":"atk,4480;","attr3":"atk,4480;hit,249;parry,166;","attr4":"def,4480;arp,166;critical,166;","attr5":"hp,40300;dodge,249;resilience,166;","hall_stone_limit":290,"hall_stone_output":29,"hall_wood_limit":290,"hall_wood_output":29,"level":20,"monster_reward":"20377,29,44;20378,29,44;","output":"20377,29;20378,29;","store_limit":"20377,290;20378,290;","update_cost1":"20377,5600;20378,9340;","update_cost2":"","update_cost3":"20377,5600;20378,1870;","update_cost4":"20377,5600;20378,1870;","update_cost5":"20377,1870;20378,5600;","update_limit":76},"21":{"attr1":"atk,4770;","attr3":"atk,4770;hit,265;parry,177;","attr4":"def,4770;arp,177;critical,177;","attr5":"hp,43000;dodge,265;resilience,177;","hall_stone_limit":310,"hall_stone_output":31,"hall_wood_limit":310,"hall_wood_output":31,"level":21,"monster_reward":"20377,31,47;20378,31,47;","output":"20377,31;20378,31;","store_limit":"20377,310;20378,310;","update_cost1":"20377,6380;20378,10630;","update_cost2":"","update_cost3":"20377,6380;20378,2130;","update_cost4":"20377,6380;20378,2130;","update_cost5":"20377,2130;20378,6380;","update_limit":78},"22":{"attr1":"atk,5070;","attr3":"atk,5070;hit,282;parry,188;","attr4":"def,5070;arp,188;critical,188;","attr5":"hp,45600;dodge,282;resilience,188;","hall_stone_limit":330,"hall_stone_output":33,"hall_wood_limit":330,"hall_wood_output":33,"level":22,"monster_reward":"20377,33,50;20378,33,50;","output":"20377,33;20378,33;","store_limit":"20377,330;20378,330;","update_cost1":"20377,7230;20378,12050;","update_cost2":"","update_cost3":"20377,7230;20378,2410;","update_cost4":"20377,7230;20378,2410;","update_cost5":"20377,2410;20378,7230;","update_limit":80},"23":{"attr1":"atk,5370;","attr3":"atk,5370;hit,299;parry,199;","attr4":"def,5380;arp,199;critical,199;","attr5":"hp,48400;dodge,299;resilience,199;","hall_stone_limit":350,"hall_stone_output":35,"hall_wood_limit":350,"hall_wood_output":35,"level":23,"monster_reward":"20377,35,53;20378,35,53;","output":"20377,35;20378,35;","store_limit":"20377,350;20378,350;","update_cost1":"20377,8140;20378,13560;","update_cost2":"","update_cost3":"20377,8140;20378,2710;","update_cost4":"20377,8140;20378,2710;","update_cost5":"20377,2710;20378,8140;","update_limit":82},"24":{"attr1":"atk,5690;","attr3":"atk,5690;hit,316;parry,211;","attr4":"def,5690;arp,211;critical,211;","attr5":"hp,51200;dodge,316;resilience,211;","hall_stone_limit":370,"hall_stone_output":37,"hall_wood_limit":370,"hall_wood_output":37,"level":24,"monster_reward":"20377,37,56;20378,37,56;","output":"20377,37;20378,37;","store_limit":"20377,370;20378,370;","update_cost1":"20377,9100;20378,15170;","update_cost2":"","update_cost3":"20377,9100;20378,3030;","update_cost4":"20377,9100;20378,3030;","update_cost5":"20377,3030;20378,9100;","update_limit":84},"25":{"attr1":"atk,6010;","attr3":"atk,6010;hit,334;parry,223;","attr4":"def,6010;arp,223;critical,223;","attr5":"hp,54100;dodge,334;resilience,223;","hall_stone_limit":390,"hall_stone_output":39,"hall_wood_limit":390,"hall_wood_output":39,"level":25,"monster_reward":"20377,39,59;20378,39,59;","output":"20377,39;20378,39;","store_limit":"20377,390;20378,390;","update_cost1":"20377,10150;20378,16920;","update_cost2":"","update_cost3":"20377,10150;20378,3380;","update_cost4":"20377,10150;20378,3380;","update_cost5":"20377,3380;20378,10150;","update_limit":86},"26":{"attr1":"atk,6330;","attr3":"atk,6330;hit,352;parry,235;","attr4":"def,6330;arp,235;critical,235;","attr5":"hp,57000;dodge,352;resilience,235;","hall_stone_limit":410,"hall_stone_output":41,"hall_wood_limit":410,"hall_wood_output":41,"level":26,"monster_reward":"20377,41,62;20378,41,62;","output":"20377,41;20378,41;","store_limit":"20377,410;20378,410;","update_cost1":"20377,11250;20378,18740;","update_cost2":"","update_cost3":"20377,11250;20378,3750;","update_cost4":"20377,11250;20378,3750;","update_cost5":"20377,3750;20378,11250;","update_limit":88},"27":{"attr1":"atk,6670;","attr3":"atk,6670;hit,371;parry,247;","attr4":"def,6670;arp,247;critical,247;","attr5":"hp,60000;dodge,371;resilience,247;","hall_stone_limit":430,"hall_stone_output":43,"hall_wood_limit":430,"hall_wood_output":43,"level":27,"monster_reward":"20377,43,65;20378,43,65;","output":"20377,43;20378,43;","store_limit":"20377,430;20378,430;","update_cost1":"20377,12430;20378,20710;","update_cost2":"","update_cost3":"20377,12430;20378,4140;","update_cost4":"20377,12430;20378,4140;","update_cost5":"20377,4140;20378,12430;","update_limit":90},"28":{"attr1":"atk,7010;","attr3":"atk,7010;hit,390;parry,260;","attr4":"def,7010;arp,260;critical,260;","attr5":"hp,63100;dodge,390;resilience,260;","hall_stone_limit":450,"hall_stone_output":45,"hall_wood_limit":450,"hall_wood_output":45,"level":28,"monster_reward":"20377,45,68;20378,45,68;","output":"20377,45;20378,45;","store_limit":"20377,450;20378,450;","update_cost1":"20377,13650;20378,22750;","update_cost2":"","update_cost3":"20377,13650;20378,4550;","update_cost4":"20377,13650;20378,4550;","update_cost5":"20377,4550;20378,13650;","update_limit":92},"29":{"attr1":"atk,7350;","attr3":"atk,7350;hit,409;parry,273;","attr4":"def,7350;arp,273;critical,273;","attr5":"hp,66200;dodge,409;resilience,273;","hall_stone_limit":470,"hall_stone_output":47,"hall_wood_limit":470,"hall_wood_output":47,"level":29,"monster_reward":"20377,47,71;20378,47,71;","output":"20377,47;20378,47;","store_limit":"20377,470;20378,470;","update_cost1":"20377,14960;20378,24940;","update_cost2":"","update_cost3":"20377,14960;20378,4990;","update_cost4":"20377,14960;20378,4990;","update_cost5":"20377,4990;20378,14960;","update_limit":94},"3":{"attr1":"atk,640;","attr3":"atk,640;hit,36;parry,24;","attr4":"def,640;arp,24;critical,24;","attr5":"hp,5800;dodge,36;resilience,24;","hall_stone_limit":120,"hall_stone_output":12,"hall_wood_limit":120,"hall_wood_output":12,"level":3,"monster_reward":"20377,12,18;20378,12,18;","output":"20377,12;20378,12;","store_limit":"20377,120;20378,120;","update_cost1":"20377,220;20378,370;","update_cost2":"","update_cost3":"20377,220;20378,70;","update_cost4":"20377,220;20378,70;","update_cost5":"20377,70;20378,220;","update_limit":42},"30":{"attr1":"atk,7710;","attr3":"atk,7710;hit,429;parry,286;","attr4":"def,7710;arp,286;critical,286;","attr5":"hp,69400;dodge,429;resilience,286;","hall_stone_limit":490,"hall_stone_output":49,"hall_wood_limit":490,"hall_wood_output":49,"level":30,"monster_reward":"20377,49,74;20378,49,74;","output":"20377,49;20378,49;","store_limit":"20377,490;20378,490;","update_cost1":"20377,16330;20378,27220;","update_cost2":"","update_cost3":"20377,16330;20378,5440;","update_cost4":"20377,16330;20378,5440;","update_cost5":"20377,5440;20378,16330;","update_limit":96},"31":{"attr1":"atk,8070;","attr3":"atk,8070;hit,449;parry,299;","attr4":"def,8070;arp,299;critical,299;","attr5":"hp,72600;dodge,449;resilience,299;","hall_stone_limit":510,"hall_stone_output":51,"hall_wood_limit":510,"hall_wood_output":51,"level":31,"monster_reward":"20377,51,77;20378,51,77;","output":"20377,51;20378,51;","store_limit":"20377,510;20378,510;","update_cost1":"20377,17760;20378,29590;","update_cost2":"","update_cost3":"20377,17760;20378,5920;","update_cost4":"20377,17760;20378,5920;","update_cost5":"20377,5920;20378,17760;","update_limit":98},"32":{"attr1":"atk,8440;","attr3":"atk,8440;hit,469;parry,313;","attr4":"def,8440;arp,313;critical,313;","attr5":"hp,76000;dodge,469;resilience,313;","hall_stone_limit":530,"hall_stone_output":53,"hall_wood_limit":530,"hall_wood_output":53,"level":32,"monster_reward":"20377,53,80;20378,53,80;","output":"20377,53;20378,53;","store_limit":"20377,530;20378,530;","update_cost1":"20377,19240;20378,32060;","update_cost2":"","update_cost3":"20377,19240;20378,6410;","update_cost4":"20377,19240;20378,6410;","update_cost5":"20377,6410;20378,19240;","update_limit":100},"33":{"attr1":"atk,8820;","attr3":"atk,8820;hit,490;parry,327;","attr4":"def,8820;arp,327;critical,327;","attr5":"hp,79400;dodge,490;resilience,327;","hall_stone_limit":550,"hall_stone_output":55,"hall_wood_limit":550,"hall_wood_output":55,"level":33,"monster_reward":"20377,55,83;20378,55,83;","output":"20377,55;20378,55;","store_limit":"20377,550;20378,550;","update_cost1":"20377,20780;20378,34630;","update_cost2":"","update_cost3":"20377,20780;20378,6930;","update_cost4":"20377,20780;20378,6930;","update_cost5":"20377,6930;20378,20780;","update_limit":102},"34":{"attr1":"atk,9200;","attr3":"atk,9200;hit,512;parry,341;","attr4":"def,9200;arp,341;critical,341;","attr5":"hp,82800;dodge,512;resilience,341;","hall_stone_limit":570,"hall_stone_output":57,"hall_wood_limit":570,"hall_wood_output":57,"level":34,"monster_reward":"20377,57,86;20378,57,86;","output":"20377,57;20378,57;","store_limit":"20377,570;20378,570;","update_cost1":"20377,22390;20378,37320;","update_cost2":"","update_cost3":"20377,22390;20378,7460;","update_cost4":"20377,22390;20378,7460;","update_cost5":"20377,7460;20378,22390;","update_limit":104},"35":{"attr1":"atk,9590;","attr3":"atk,9590;hit,533;parry,356;","attr4":"def,9590;arp,356;critical,356;","attr5":"hp,86300;dodge,533;resilience,356;","hall_stone_limit":590,"hall_stone_output":59,"hall_wood_limit":590,"hall_wood_output":59,"level":35,"monster_reward":"20377,59,89;20378,59,89;","output":"20377,59;20378,59;","store_limit":"20377,590;20378,590;","update_cost1":"20377,24060;20378,40100;","update_cost2":"","update_cost3":"20377,24060;20378,8020;","update_cost4":"20377,24060;20378,8020;","update_cost5":"20377,8020;20378,24060;","update_limit":106},"36":{"attr1":"atk,9990;","attr3":"atk,9990;hit,555;parry,370;","attr4":"def,9990;arp,370;critical,370;","attr5":"hp,89900;dodge,555;resilience,370;","hall_stone_limit":610,"hall_stone_output":61,"hall_wood_limit":610,"hall_wood_output":61,"level":36,"monster_reward":"20377,61,92;20378,61,92;","output":"20377,61;20378,61;","store_limit":"20377,610;20378,610;","update_cost1":"20377,25790;20378,42980;","update_cost2":"","update_cost3":"20377,25790;20378,8600;","update_cost4":"20377,25790;20378,8600;","update_cost5":"20377,8600;20378,25790;","update_limit":108},"37":{"attr1":"atk,10390;","attr3":"atk,10390;hit,578;parry,385;","attr4":"def,10390;arp,385;critical,385;","attr5":"hp,93600;dodge,578;resilience,385;","hall_stone_limit":630,"hall_stone_output":63,"hall_wood_limit":630,"hall_wood_output":63,"level":37,"monster_reward":"20377,63,95;20378,63,95;","output":"20377,63;20378,63;","store_limit":"20377,630;20378,630;","update_cost1":"20377,27560;20378,45940;","update_cost2":"","update_cost3":"20377,27560;20378,9190;","update_cost4":"20377,27560;20378,9190;","update_cost5":"20377,9190;20378,27560;","update_limit":110},"38":{"attr1":"atk,10810;","attr3":"atk,10810;hit,601;parry,401;","attr4":"def,10810;arp,401;critical,401;","attr5":"hp,97300;dodge,601;resilience,401;","hall_stone_limit":650,"hall_stone_output":65,"hall_wood_limit":650,"hall_wood_output":65,"level":38,"monster_reward":"20377,65,98;20378,65,98;","output":"20377,65;20378,65;","store_limit":"20377,650;20378,650;","update_cost1":"20377,29400;20378,49010;","update_cost2":"","update_cost3":"20377,29400;20378,9800;","update_cost4":"20377,29400;20378,9800;","update_cost5":"20377,9800;20378,29400;","update_limit":112},"39":{"attr1":"atk,11230;","attr3":"atk,11230;hit,624;parry,416;","attr4":"def,11230;arp,416;critical,416;","attr5":"hp,101000;dodge,624;resilience,416;","hall_stone_limit":670,"hall_stone_output":67,"hall_wood_limit":670,"hall_wood_output":67,"level":39,"monster_reward":"20377,67,101;20378,67,101;","output":"20377,67;20378,67;","store_limit":"20377,670;20378,670;","update_cost1":"20377,31320;20378,52200;","update_cost2":"","update_cost3":"20377,31320;20378,10440;","update_cost4":"20377,31320;20378,10440;","update_cost5":"20377,10440;20378,31320;","update_limit":114},"4":{"attr1":"atk,810;","attr3":"atk,810;hit,45;parry,30;","attr4":"def,810;arp,30;critical,30;","attr5":"hp,7300;dodge,45;resilience,30;","hall_stone_limit":130,"hall_stone_output":13,"hall_wood_limit":130,"hall_wood_output":13,"level":4,"monster_reward":"20377,13,20;20378,13,20;","output":"20377,13;20378,13;","store_limit":"20377,130;20378,130;","update_cost1":"20377,340;20378,560;","update_cost2":"","update_cost3":"20377,340;20378,110;","update_cost4":"20377,340;20378,110;","update_cost5":"20377,110;20378,340;","update_limit":44},"40":{"attr1":"atk,11650;","attr3":"atk,11650;hit,648;parry,432;","attr4":"def,11650;arp,432;critical,432;","attr5":"hp,104900;dodge,648;resilience,432;","hall_stone_limit":690,"hall_stone_output":69,"hall_wood_limit":690,"hall_wood_output":69,"level":40,"monster_reward":"20377,69,104;20378,69,104;","output":"20377,69;20378,69;","store_limit":"20377,690;20378,690;","update_cost1":"20377,33290;20378,55490;","update_cost2":"","update_cost3":"20377,33290;20378,11100;","update_cost4":"20377,33290;20378,11100;","update_cost5":"20377,11100;20378,33290;","update_limit":116},"5":{"attr1":"atk,990;","attr3":"atk,990;hit,55;parry,37;","attr4":"def,990;arp,37;critical,37;","attr5":"hp,8900;dodge,55;resilience,37;","hall_stone_limit":140,"hall_stone_output":14,"hall_wood_limit":140,"hall_wood_output":14,"level":5,"monster_reward":"20377,14,21;20378,14,21;","output":"20377,14;20378,14;","store_limit":"20377,140;20378,140;","update_cost1":"20377,480;20378,810;","update_cost2":"","update_cost3":"20377,480;20378,160;","update_cost4":"20377,480;20378,160;","update_cost5":"20377,160;20378,480;","update_limit":46},"6":{"attr1":"atk,1170;","attr3":"atk,1170;hit,65;parry,43;","attr4":"def,1170;arp,43;critical,43;","attr5":"hp,10500;dodge,65;resilience,43;","hall_stone_limit":150,"hall_stone_output":15,"hall_wood_limit":150,"hall_wood_output":15,"level":6,"monster_reward":"20377,15,23;20378,15,23;","output":"20377,15;20378,15;","store_limit":"20377,150;20378,150;","update_cost1":"20377,660;20378,1090;","update_cost2":"","update_cost3":"20377,660;20378,220;","update_cost4":"20377,660;20378,220;","update_cost5":"20377,220;20378,660;","update_limit":48},"7":{"attr1":"atk,1360;","attr3":"atk,1360;hit,76;parry,50;","attr4":"def,1360;arp,50;critical,50;","attr5":"hp,12200;dodge,76;resilience,50;","hall_stone_limit":160,"hall_stone_output":16,"hall_wood_limit":160,"hall_wood_output":16,"level":7,"monster_reward":"20377,16,24;20378,16,24;","output":"20377,16;20378,16;","store_limit":"20377,160;20378,160;","update_cost1":"20377,890;20378,1490;","update_cost2":"","update_cost3":"20377,890;20378,300;","update_cost4":"20377,890;20378,300;","update_cost5":"20377,300;20378,890;","update_limit":50},"8":{"attr1":"atk,1560;","attr3":"atk,1560;hit,87;parry,58;","attr4":"def,1560;arp,58;critical,58;","attr5":"hp,14000;dodge,87;resilience,58;","hall_stone_limit":170,"hall_stone_output":17,"hall_wood_limit":170,"hall_wood_output":17,"level":8,"monster_reward":"20377,17,26;20378,17,26;","output":"20377,17;20378,17;","store_limit":"20377,170;20378,170;","update_cost1":"20377,1180;20378,1970;","update_cost2":"","update_cost3":"20377,1180;20378,390;","update_cost4":"20377,1180;20378,390;","update_cost5":"20377,390;20378,1180;","update_limit":52},"9":{"attr1":"atk,1760;","attr3":"atk,1760;hit,98;parry,65;","attr4":"def,1760;arp,65;critical,65;","attr5":"hp,15800;dodge,98;resilience,65;","hall_stone_limit":180,"hall_stone_output":18,"hall_wood_limit":180,"hall_wood_output":18,"level":9,"monster_reward":"20377,18,27;20378,18,27;","output":"20377,18;20378,18;","store_limit":"20377,180;20378,180;","update_cost1":"20377,1380;20378,2300;","update_cost2":"","update_cost3":"20377,1380;20378,460;","update_cost4":"20377,1380;20378,460;","update_cost5":"20377,460;20378,1380;","update_limit":54}}